<preface xmlns="http://docbook.org/ns/docbook" 
        version="5.0"

        xmlns:xlink="http://www.w3.org/1999/xlink"
        xml:id="preface"
    >

<info>
    <title>Pathagar Documentation Project</title>
    <author>
        <orgname>olpcSF.org</orgname>
    </author>
    <copyright>
        <year>2016</year>
        <holder>Alex Kleider</holder>
    </copyright>
</info>

<formalpara>
    <title>Copyright Information</title>
    <para>
        This material is released under a 

        <link xlink:href="http://creativecommons.org/licenses">
        CreativeCommons
        </link>

        license.
    </para>
</formalpara>

<para>
    The goal of this document, a project of 

    <link xlink:href="http://www.olpcsf.org/">
    olpcSF.org
    </link>

    , is to provide 
    helpful documentation of the pathagar book server project and more
    specifically to help with installation, configuration and usage 
    of this service software on low energy requiring hardware.  We began
    with the DreamPlug but have since switched to the Raspberry Pi as
    our device of choice.
</para>

</preface>

